pxm/__init__.py
pxm/dic.py
pxm/exists.py
pxm/read.py
pxm/write.py
pxm-1.0.3.dist-info/LICENSE
pxm-1.0.3.dist-info/METADATA
pxm-1.0.3.dist-info/WHEEL
pxm-1.0.3.dist-info/top_level.txt
pxm-1.0.3.dist-info/RECORD
