Metadata-Version: 2.1
Name: pxm
Version: 1.0.3
Summary: 这是一个Python编写的表格读写常用操作功能基础模块，使用了三种引擎进行封装,屏蔽各种引擎实现方式,统一方法
Home-page: https://gitee.com/liumou_site/pxm
Author: 坐公交也用券
Author-email: liumou.site@qq.com
License: UNKNOWN
Platform: UNKNOWN
Classifier: Programming Language :: Python :: 3
Classifier: License :: OSI Approved :: MIT License
Classifier: Operating System :: OS Independent
Requires-Python: >=3.6
Requires-Dist: ColorInfo3 (==2.1.1)
Requires-Dist: openpyxl (~=3.1.1)
